planning_poker/__init__.py
planning_poker/admin.py
planning_poker/apps.py
planning_poker/constants.py
planning_poker/consumers.py
planning_poker/models.py
planning_poker/receivers.py
planning_poker/routing.py
planning_poker/urls.py
planning_poker/version.py
planning_poker/views.py
planning_poker/locale/de/LC_MESSAGES/django.mo
planning_poker/locale/de/LC_MESSAGES/django.po
planning_poker/locale/de/LC_MESSAGES/djangojs.mo
planning_poker/locale/de/LC_MESSAGES/djangojs.po
planning_poker/locale/en/LC_MESSAGES/django.mo
planning_poker/locale/en/LC_MESSAGES/django.po
planning_poker/locale/en/LC_MESSAGES/djangojs.mo
planning_poker/locale/en/LC_MESSAGES/djangojs.po
planning_poker/migrations/0001_initial.py
planning_poker/migrations/__init__.py
planning_poker/static/planning_poker/css/poker.css
planning_poker/static/planning_poker/favicons/android-chrome-144x144.png
planning_poker/static/planning_poker/favicons/apple-touch-icon.png
planning_poker/static/planning_poker/favicons/favicon-16x16.png
planning_poker/static/planning_poker/favicons/favicon-32x32.png
planning_poker/static/planning_poker/favicons/favicon.ico
planning_poker/static/planning_poker/favicons/mstile-150x150.png
planning_poker/static/planning_poker/favicons/safari-pinned-tab.svg
planning_poker/static/planning_poker/js/header-app.js
planning_poker/static/planning_poker/js/header-app.js.LICENSE.txt
planning_poker/static/planning_poker/js/poker-session.js
planning_poker/static/planning_poker/js/poker-session.js.LICENSE.txt
planning_poker/templates/admin/dropdown_filter.html
planning_poker/templates/planning_poker/base.html
planning_poker/templates/planning_poker/index.html
planning_poker/templates/planning_poker/poker_session.html
planning_poker-1.0.3.dist-info/AUTHORS.rst
planning_poker-1.0.3.dist-info/LICENSE
planning_poker-1.0.3.dist-info/METADATA
planning_poker-1.0.3.dist-info/WHEEL
planning_poker-1.0.3.dist-info/top_level.txt
planning_poker-1.0.3.dist-info/RECORD
